ddv/__init__.py
ddv/logging/__init__.py
ddv_logging-0.3.0.dist-info/LICENSE.md
ddv_logging-0.3.0.dist-info/WHEEL
ddv_logging-0.3.0.dist-info/METADATA
ddv_logging-0.3.0.dist-info/RECORD
