Metadata-Version: 2.1
Name: ddv-logging
Version: 0.3.0
Summary: Python logging formatters, filters, and convenience methods
Home-page: https://gitlab.com/davidevi/ddv-logging
License: Unlicense
Keywords: ddv,logging,colour,color,indent,indentation,verbose,verbosity
Author: Davide Vitelaru
Author-email: davide@vitelaru.com
Maintainer: Davide Vitelaru
Maintainer-email: davide@vitelaru.com
Requires-Python: >=3.7,<4.0
Classifier: License :: Other/Proprietary License
Classifier: Programming Language :: Python :: 3
Classifier: Programming Language :: Python :: 3.7
Classifier: Programming Language :: Python :: 3.8
Classifier: Programming Language :: Python :: 3.9
Project-URL: Repository, https://gitlab.com/davidevi/ddv-logging
